cv2obs/README.MD
cv2obs/__init__.py
cv2obs/cv2obs.py
cv2obs/cv2obscam.py
cv2obs/requirements.txt
cv2obs/thirdparty.json
cv2obs-0.10.dist-info/LICENSE.rst
cv2obs-0.10.dist-info/METADATA
cv2obs-0.10.dist-info/WHEEL
cv2obs-0.10.dist-info/top_level.txt
cv2obs-0.10.dist-info/RECORD
