Metadata-Version: 2.1
Name: cv2obs
Version: 0.10
Summary: OpenCV Images (NumPy Arrays) to OBS Virtual Cam
Home-page: https://github.com/hansalemaos/cv2obs
Author: Johannes Fischer
Author-email: aulasparticularesdealemaosp@gmail.com
License: MIT
Keywords: cv2,imshow,obs,stream,virtual,cam
Classifier: Development Status :: 4 - Beta
Classifier: Programming Language :: Python :: 3 :: Only
Classifier: Programming Language :: Python :: 3.10
Classifier: Topic :: Software Development :: Libraries :: Python Modules
Classifier: Topic :: Utilities
License-File: LICENSE.rst
Requires-Dist: a-cv2-easy-resize
Requires-Dist: a-cv-imwrite-imread-plus
Requires-Dist: hackyargparser
Requires-Dist: keyboard
Requires-Dist: numpy
Requires-Dist: opencv-python
Requires-Dist: pyvirtualcam
Requires-Dist: subprocess-multipipe
Requires-Dist: varpickler
